cedar_policy/__about__.py
cedar_policy/__init__.py
cedar_policy-0.0.1.dist-info/METADATA
cedar_policy-0.0.1.dist-info/WHEEL
cedar_policy-0.0.1.dist-info/licenses/LICENSE.txt
cedar_policy-0.0.1.dist-info/RECORD
